{
  "version": 1,
  "serviceConfiguration": {
    "apiName": "projectportfolio",
    "serviceName": "AppSync",
    "gqlSchemaPath": "C:\\Users\\byron\\project-portfolio\\amplify\\backend\\api\\projectportfolio\\schema.graphql",
    "defaultAuthType": {
      "mode": "AMAZON_COGNITO_USER_POOLS",
      "cognitoUserPoolId": "authprojectportfolio8428fd2b"
    },
    "additionalAuthTypes": [
      {
        "mode": "AWS_IAM"
      },
      {
        "mode": "API_KEY",
        "expirationTime": 7,
        "apiKeyExpirationDate": "2022-02-05T15:44:55.326Z",
        "keyDescription": "Get projects"
      }
    ],
    "conflictResolution": {}
  }
}